libreface/__init__.py
libreface/commandline.py
libreface/detect_mediapipe_image.py
libreface/utils.py
libreface/AU_Detection/__init__.py
libreface/AU_Detection/inference.py
libreface/AU_Detection/solver_inference_image.py
libreface/AU_Detection/models/__init__.py
libreface/AU_Detection/models/resnet18.py
libreface/AU_Recognition/__init__.py
libreface/AU_Recognition/inference.py
libreface/AU_Recognition/solver_inference_combine.py
libreface/AU_Recognition/solver_inference_image.py
libreface/AU_Recognition/models/__init__.py
libreface/AU_Recognition/models/mae.py
libreface/AU_Recognition/models/masking_generator.py
libreface/AU_Recognition/models/resnet18.py
libreface/AU_Recognition/models/resnet18_combine.py
libreface/Facial_Expression_Recognition/__init__.py
libreface/Facial_Expression_Recognition/inference.py
libreface/Facial_Expression_Recognition/solver_inference_image.py
libreface/Facial_Expression_Recognition/models/__init__.py
libreface/Facial_Expression_Recognition/models/resnet18.py
libreface-0.1.1.dist-info/LICENSE.rst
libreface-0.1.1.dist-info/METADATA
libreface-0.1.1.dist-info/WHEEL
libreface-0.1.1.dist-info/entry_points.txt
libreface-0.1.1.dist-info/top_level.txt
libreface-0.1.1.dist-info/RECORD
