Metadata-Version: 2.1
Name: libreface
Version: 0.1.1
Summary: LibreFace model for facial analysis
Home-page: https://boese0601.github.io/libreface
Author: IHP-Lab
Author-email: achaubey@usc.edu
License: USC Research Licence 
Classifier: Programming Language :: Python
Classifier: Programming Language :: Python :: 3
Classifier: Programming Language :: Python :: 3.9
Classifier: Programming Language :: Python :: Implementation :: CPython
Classifier: Programming Language :: Python :: Implementation :: PyPy
Requires-Python: >=3.9
License-File: LICENSE.rst
Requires-Dist: bleach !=5.0.0
Requires-Dist: cmake ==3.30.3
Requires-Dist: dlib ==19.24.6
Requires-Dist: gdown ==5.2.0
Requires-Dist: importlib-metadata ==8.4.0
Requires-Dist: importlib-resources ==6.4.5
Requires-Dist: imutils ==0.5.4
Requires-Dist: mediapipe ==0.10.5
Requires-Dist: oauthlib >=3.0.0
Requires-Dist: opencv-python ==4.10.0.84
Requires-Dist: pandas ==2.0.3
Requires-Dist: pyyaml ==6.0.2
Requires-Dist: requests ==2.32.3
Requires-Dist: scikit-learn ==1.3.2
Requires-Dist: timm ==1.0.9
Requires-Dist: torch ==2.0.0
Requires-Dist: torchaudio ==2.0.1
Requires-Dist: torchvision ==0.15.1
Requires-Dist: tqdm ==4.66.5
